nonebot_plugin_longtu-0.1.1.post1.dist-info/METADATA
nonebot_plugin_longtu-0.1.1.post1.dist-info/WHEEL
nonebot_plugin_longtu-0.1.1.post1.dist-info/licenses/LICENSE
nonebot_plugin_longtu/__init__.py
nonebot_plugin_longtu/config.py
nonebot_plugin_longtu-0.1.1.post1.dist-info/RECORD
